{
	"name": "Storage event trigger",
	"properties": {
		"annotations": [],
		"runtimeState": "Started",
		"pipelines": [
			{
				"pipelineReference": {
					"referenceName": "Copy activity",
					"type": "PipelineReference"
				}
			}
		],
		"type": "BlobEventsTrigger",
		"typeProperties": {
			"blobPathBeginsWith": "/input-aws/blobs/",
			"blobPathEndsWith": ".json",
			"ignoreEmptyBlobs": true,
			"scope": "/subscriptions/63a10f88-4534-476a-b0ff-a850246ac2af/resourceGroups/project001/providers/Microsoft.Storage/storageAccounts/projectde01blob",
			"events": [
				"Microsoft.Storage.BlobCreated"
			]
		}
	}
}